LICENSE
MANIFEST.in
README.md
setup.py
doc/Makefile
doc/source/conf.py
doc/source/index.rst
sqltap/__init__.py
sqltap/sqltap.py
sqltap/wsgi.py
sqltap/templates/html.mako
sqltap/templates/text.mako
sqltap/templates/wsgi.mako
sqltap_ng.egg-info/PKG-INFO
sqltap_ng.egg-info/SOURCES.txt
sqltap_ng.egg-info/dependency_links.txt
sqltap_ng.egg-info/requires.txt
sqltap_ng.egg-info/top_level.txt