Metadata-Version: 1.1
Name: sqltap-ng
Version: 0.3.11
Summary: Profiling and introspection for applications using sqlalchemy
Home-page: https://github.com/inconshreveable/sqltap
Author: inconshreveable
Author-email: alan@inconshreveable.com
License: UNKNOWN
Platform: UNKNOWN
Classifier: Development Status :: 4 - Beta
Classifier: Intended Audience :: Developers
Classifier: License :: OSI Approved :: Apache Software License
Classifier: Operating System :: OS Independent
Classifier: Programming Language :: Python
Classifier: Programming Language :: Python :: 3
Classifier: Topic :: Database
